pelican/plugins/seafoam/__init__.py
pelican/plugins/seafoam/constants.py
pelican/plugins/seafoam/debug.py
pelican/plugins/seafoam/formatting.py
pelican/plugins/seafoam/initialize.py
pelican/plugins/seafoam/static/css/bootstrap.seafoam.min.css
pelican/plugins/seafoam/static/css/bootstrap.strathcona.min.css
pelican/plugins/seafoam/static/fonts/fa-brands-400.ttf
pelican/plugins/seafoam/static/fonts/fa-brands-400.woff2
pelican/plugins/seafoam/static/fonts/fa-regular-400.ttf
pelican/plugins/seafoam/static/fonts/fa-regular-400.woff2
pelican/plugins/seafoam/static/fonts/fa-solid-900.ttf
pelican/plugins/seafoam/static/fonts/fa-solid-900.woff2
pelican/plugins/seafoam/static/fonts/fa-v4compatibility.ttf
pelican/plugins/seafoam/static/fonts/fa-v4compatibility.woff2
pelican/plugins/seafoam/static/fonts/glyphicons-halflings-regular.eot
pelican/plugins/seafoam/static/fonts/glyphicons-halflings-regular.svg
pelican/plugins/seafoam/static/fonts/glyphicons-halflings-regular.ttf
pelican/plugins/seafoam/static/fonts/glyphicons-halflings-regular.woff
pelican/plugins/seafoam/static/fonts/glyphicons-halflings-regular.woff2
pelican/plugins/seafoam/static/fonts/cabin/FONTLOG.txt
pelican/plugins/seafoam/static/fonts/cabin/OFL.txt
pelican/plugins/seafoam/static/fonts/cabin/cabin-v34-latin-700.woff2
pelican/plugins/seafoam/static/fonts/cabin/cabin-v34-latin-700italic.woff2
pelican/plugins/seafoam/static/fonts/cabin/cabin-v34-latin-italic.woff2
pelican/plugins/seafoam/static/fonts/cabin/cabin-v34-latin-regular.woff2
pelican/plugins/seafoam/static/fonts/eb-garamond/eb-garamond-v31-latin-700.woff2
pelican/plugins/seafoam/static/fonts/eb-garamond/eb-garamond-v31-latin-700italic.woff2
pelican/plugins/seafoam/static/fonts/eb-garamond/eb-garamond-v31-latin-italic.woff2
pelican/plugins/seafoam/static/fonts/eb-garamond/eb-garamond-v31-latin-regular.woff2
pelican/plugins/seafoam/static/fonts/expletus-sans/OFL.txt
pelican/plugins/seafoam/static/fonts/expletus-sans/expletus-sans-v30-latin-500.woff2
seafoam-2.16.0.dist-info/licenses/LICENSE.txt
seafoam-2.16.0.dist-info/METADATA
seafoam-2.16.0.dist-info/WHEEL
seafoam-2.16.0.dist-info/top_level.txt
seafoam-2.16.0.dist-info/RECORD
