Metadata-Version: 2.4
Name: seafoam
Version: 2.16.0
Summary: Pelican theme, first used for Minchin.ca.
Author-email: William Minchin <w_minchin@hotmail.com>
Maintainer-email: William Minchin <w_minchin@hotmail.com>
License-Expression: MIT
Project-URL: Bug Tracker, https://github.com/MinchinWeb/seafoam/issues
Project-URL: Repository, https://github.com/MinchinWeb/seafoam
Project-URL: Changelog, https://github.com/MinchinWeb/seafoam/blob/master/docs/changelog.rst
Classifier: Development Status :: 5 - Production/Stable
Classifier: Environment :: Console
Classifier: Framework :: Pelican :: Plugins
Classifier: Programming Language :: Python :: 3
Classifier: Programming Language :: Python :: 3.9
Classifier: Programming Language :: Python :: 3.10
Classifier: Programming Language :: Python :: 3.11
Classifier: Programming Language :: Python :: 3.12
Classifier: Programming Language :: Python :: 3.13
Classifier: Programming Language :: Python :: 3.14
Classifier: Programming Language :: Python :: 3 :: Only
Classifier: Natural Language :: English
Classifier: Intended Audience :: Developers
Classifier: Operating System :: OS Independent
Classifier: Topic :: Software Development :: Libraries :: Python Modules
License-File: LICENSE.txt
Requires-Dist: pelican
Requires-Dist: pelican-image-process>=2.1.1
Requires-Dist: pelican-jinja-filters>=2.1.0
Requires-Dist: packaging
Requires-Dist: beautifulsoup4
Provides-Extra: lxml
Requires-Dist: lxml; extra == "lxml"
Provides-Extra: build
Requires-Dist: minchin.releaser>=0.8.2; extra == "build"
Requires-Dist: pygments; extra == "build"
Provides-Extra: docs
Provides-Extra: test
Requires-Dist: markdown; extra == "test"
Provides-Extra: dev
Requires-Dist: markdown; extra == "dev"
Requires-Dist: invoke; extra == "dev"
Provides-Extra: lint
Requires-Dist: black; extra == "lint"
Requires-Dist: isort; extra == "lint"
Dynamic: license-file
